{"chunk_definitions":[{"chunk_id":"cfo5u1y7qg5y4","chunk_label":"unnamed-chunk-1","document_id":"768B6F34","expansion_state":0,"options":{"engine":"r","label":"unnamed-chunk-1"},"row":21,"row_count":1,"visible":true},{"chunk_id":"c5ux32w6yiqne","chunk_label":"unnamed-chunk-5","document_id":"768B6F34","expansion_state":0,"options":{"engine":"r","label":"unnamed-chunk-14"},"row":71,"row_count":1,"visible":true},{"chunk_id":"cexlt0a16yhsy","chunk_label":"unnamed-chunk-6","document_id":"768B6F34","expansion_state":0,"options":{"engine":"r","label":"unnamed-chunk-15"},"row":85,"row_count":1,"visible":true},{"chunk_id":"cdg7c8ymlt4gh","chunk_label":"unnamed-chunk-7","document_id":"768B6F34","expansion_state":0,"options":{"engine":"r","label":"unnamed-chunk-8"},"row":92,"row_count":1,"visible":true},{"chunk_id":"cmncz93vqeozs","chunk_label":"unnamed-chunk-20","document_id":"768B6F34","expansion_state":0,"options":{"engine":"r","label":"unnamed-chunk-16"},"row":345,"row_count":1,"visible":true},{"chunk_id":"cuh4e4k52ue2g","chunk_label":"unnamed-chunk-28","document_id":"768B6F34","expansion_state":0,"options":{"engine":"r","label":"unnamed-chunk-1"},"row":406,"row_count":1,"visible":true},{"chunk_id":"ch68dw6hz0bq0","chunk_label":"unnamed-chunk-32","document_id":"768B6F34","expansion_state":0,"options":{"engine":"r","label":"unnamed-chunk-25"},"row":434,"row_count":1,"visible":true},{"chunk_id":"c1oufygz19gvp","chunk_label":"unnamed-chunk-33","document_id":"768B6F34","expansion_state":0,"options":{"engine":"r","label":"unnamed-chunk-11"},"row":441,"row_count":1,"visible":true}],"doc_write_time":1638671732}